yes3/__init__.py
yes3/client.py
yes3/config.py
yes3/s3.py
yes3/caching/__init__.py
yes3/caching/base.py
yes3/caching/local_cache.py
yes3/caching/memory_cache.py
yes3/caching/multi_cache.py
yes3/caching/s3_cache.py
yes3/caching/setup_helpers.py
yes3/utils/__init__.py
yes3/utils/decorators.py
yes3/utils/logs.py
yes3/utils/testing.py
yes3-0.1.3.dist-info/licenses/LICENSE
yes3-0.1.3.dist-info/METADATA
yes3-0.1.3.dist-info/WHEEL
yes3-0.1.3.dist-info/top_level.txt
yes3-0.1.3.dist-info/RECORD
