Metadata-Version: 2.4
Name: yes3
Version: 0.1.3
Summary: A simple, intuitive, flexible interface for Amazon S3
Author-email: Erik Schomburg <eschomburg@gmail.com>
Project-URL: Homepage, https://github.com/eschombu/yes3
Project-URL: Issues, https://github.com/eschombu/yes3/issues
Classifier: Programming Language :: Python :: 3
Classifier: License :: OSI Approved :: MIT License
Classifier: Operating System :: OS Independent
Requires-Python: >=3.9
License-File: LICENSE
Requires-Dist: boto3
Requires-Dist: numpy
Requires-Dist: pandas
Requires-Dist: tqdm
Provides-Extra: dev
Requires-Dist: flake8; extra == "dev"
Requires-Dist: moto; extra == "dev"
Requires-Dist: pytest; extra == "dev"
Dynamic: license-file
